JianZhiOfferDierBanQuanjieDoocsKaiyuanShequ/README.md
JianZhiOfferDierBanQuanjieDoocsKaiyuanShequ/__init__.py
JianZhiOfferDierBanQuanjieDoocsKaiyuanShequ/__main__.py
JianZhiOfferDierBanQuanjieDoocsKaiyuanShequ/file.epub
JianZhiOfferDierBanQuanjieDoocsKaiyuanShequ/index.html
JianZhiOfferDierBanQuanjieDoocsKaiyuanShequ/css/__init__.py
JianZhiOfferDierBanQuanjieDoocsKaiyuanShequ/css/annotations.css
JianZhiOfferDierBanQuanjieDoocsKaiyuanShequ/css/main.css
JianZhiOfferDierBanQuanjieDoocsKaiyuanShequ/css/normalize.css
JianZhiOfferDierBanQuanjieDoocsKaiyuanShequ/css/popup.css
JianZhiOfferDierBanQuanjieDoocsKaiyuanShequ/font/__init__.py
JianZhiOfferDierBanQuanjieDoocsKaiyuanShequ/font/fontello.eot
JianZhiOfferDierBanQuanjieDoocsKaiyuanShequ/font/fontello.svg
JianZhiOfferDierBanQuanjieDoocsKaiyuanShequ/font/fontello.ttf
JianZhiOfferDierBanQuanjieDoocsKaiyuanShequ/font/fontello.woff
JianZhiOfferDierBanQuanjieDoocsKaiyuanShequ/img/__init__.py
JianZhiOfferDierBanQuanjieDoocsKaiyuanShequ/img/annotator-glyph-sprite.png
JianZhiOfferDierBanQuanjieDoocsKaiyuanShequ/img/annotator-icon-sprite.png
JianZhiOfferDierBanQuanjieDoocsKaiyuanShequ/img/apple-touch-icon.png
JianZhiOfferDierBanQuanjieDoocsKaiyuanShequ/img/cancelfullscreen.png
JianZhiOfferDierBanQuanjieDoocsKaiyuanShequ/img/close.png
JianZhiOfferDierBanQuanjieDoocsKaiyuanShequ/img/fullscreen.png
JianZhiOfferDierBanQuanjieDoocsKaiyuanShequ/img/loader.gif
JianZhiOfferDierBanQuanjieDoocsKaiyuanShequ/img/menu-icon.png
JianZhiOfferDierBanQuanjieDoocsKaiyuanShequ/img/save.png
JianZhiOfferDierBanQuanjieDoocsKaiyuanShequ/img/saved.png
JianZhiOfferDierBanQuanjieDoocsKaiyuanShequ/img/settings-s.png
JianZhiOfferDierBanQuanjieDoocsKaiyuanShequ/img/settings.png
JianZhiOfferDierBanQuanjieDoocsKaiyuanShequ/img/star.png
JianZhiOfferDierBanQuanjieDoocsKaiyuanShequ/js/__init__.py
JianZhiOfferDierBanQuanjieDoocsKaiyuanShequ/js/epub.js
JianZhiOfferDierBanQuanjieDoocsKaiyuanShequ/js/epub.min.js
jian_zhi_offer_dier_ban_quanjie_doocs_kaiyuan_shequ-2024.3.5.0.dist-info/METADATA
jian_zhi_offer_dier_ban_quanjie_doocs_kaiyuan_shequ-2024.3.5.0.dist-info/WHEEL
jian_zhi_offer_dier_ban_quanjie_doocs_kaiyuan_shequ-2024.3.5.0.dist-info/entry_points.txt
jian_zhi_offer_dier_ban_quanjie_doocs_kaiyuan_shequ-2024.3.5.0.dist-info/top_level.txt
jian_zhi_offer_dier_ban_quanjie_doocs_kaiyuan_shequ-2024.3.5.0.dist-info/RECORD
